{
  "keys": {
    "BTX_NCDI2EDFJL": {
      "status": "ACTIVE",
      "updated": "2026-03-11T07:01:50.243267"
    },
    "BTX_MUGXI1NAU9": {
      "status": "ACTIVE",
      "updated": "2026-03-11T07:01:50.243311"
    },
    "BTX_SJ56IZV4K8": {
      "status": "ACTIVE",
      "updated": "2026-03-11T07:01:50.243320"
    },
    "BTX_M8SXIV3YEP": {
      "status": "ACTIVE",
      "updated": "2026-03-11T07:01:50.243350"
    },
    "BTX_U7EVYBUM7J": {
      "status": "ACTIVE",
      "updated": "2026-03-11T07:01:50.243360"
    },
    "BTX_VIZQDM24KY": {
      "status": "ACTIVE",
      "updated": "2026-03-11T07:01:50.243367"
    }
  }
}